[
  {
    "old": "BLACK",
    "new": "BLACK"
  },
  {
    "old": "エピローグ",
    "new": "外延",
    "checked": 0
  },
  {
    "old": "――四月の風と七月の太陽が十月の彩りをもたらす。",
    "new": "四月的风和七月的太阳带来十月的色彩。",
    "checked": 0
  },
  {
    "old": "bg008",
    "new": "bg008"
  },
  {
    "old": "bgm01",
    "new": "bgm01"
  },
  {
    "old": "佐和良義宝珠と結ばれた日から七日のときが過ぎた。",
    "new": "从和佐和良义宝珠结合之日开始，已经过了七天。",
    "checked": 0
  },
  {
    "old": "秋も深まり、黄金色と朱色の葉は木々を彩るよりも地を彩っていた。極彩色の絨毯。",
    "new": "秋意渐浓，金黄色和朱红色的叶子比起点缀树木，更为大地上色。五彩缤纷的地毯",
    "checked": 0
  },
  {
    "old": "微かだけれど確かな変化。",
    "new": "细微但确实的变化。",
    "checked": 0
  },
  {
    "old": "七日という時間は大きな――否、小さくても確かな変化を起こしていた。",
    "new": "七天的时间很大——不，即使很小也会发生确实的变化。",
    "checked": 0
  },
  {
    "old": "そのひとつは――……",
    "new": "其中之一是——…",
    "checked": 0
  },
  {
    "old": "SE_059",
    "new": "SE_059"
  },
  {
    "old": "FadeSpeedRight",
    "new": "FadeSpeedRight"
  },
  {
    "old": "bg002",
    "new": "bg002"
  },
  {
    "old": "ST_MY_21_0B",
    "new": "ST_MY_21_0B"
  },
  {
    "old": "NONE",
    "new": "NONE"
  },
  {
    "old": "宮原",
    "new": "宫原",
    "checked": 0
  },
  {
    "old": "お見事。",
    "new": "真漂亮。",
    "checked": 0
  },
  {
    "old": "Vo_miy_0033",
    "new": "Vo_miy_0033"
  },
  {
    "old": "ST_TR_21_0B",
    "new": "ST_TR_21_0B"
  },
  {
    "old": "鶴見",
    "new": "鹤见",
    "checked": 0
  },
  {
    "old": "葵に比べたらまだまだだわ。",
    "new": "和葵比起来还差得远呢。",
    "checked": 0
  },
  {
    "old": "Vo_tur_0027",
    "new": "Vo_tur_0027"
  },
  {
    "old": "宮原部長と鶴見副部長。",
    "new": "宫原部长和鹤见副部长。",
    "checked": 0
  },
  {
    "old": "謎を解くための鍵が分からず、心の乱れを正すために弓を引かせて貰ってからちょくちょくと顔を出すようになった。だから気付いたのだけど――……",
    "new": "不知道解开谜团的钥匙，为了纠正内心的混乱，请我拉弓之后，经常露面。所以才注意到了——……",
    "checked": 0
  },
  {
    "old": "ST_MY_21_0A",
    "new": "ST_MY_21_0A"
  },
  {
    "old": "かなん。汗が滲んでるぞ。",
    "new": "嗯。汗渗出来了。",
    "checked": 0
  },
  {
    "old": "Vo_miy_0034",
    "new": "Vo_miy_0034"
  },
  {
    "old": "ST_TR_21_0A",
    "new": "ST_TR_21_0A"
  },
  {
    "old": "大丈夫よ。ぁ……。",
    "new": "没关系的。啊……。",
    "checked": 0
  },
  {
    "old": "Vo_tur_0028",
    "new": "Vo_tur_0028"
  },
  {
    "old": "大丈夫と手を振る鶴見副部長を意に返さず、自分の手ぬぐいで子供にするよう丁寧に鶴見副部長の額の汗を拭った。今までは……わたしが所属してた頃はなかった情景。",
    "new": "鹤见副部长挥挥手说没事，她不理会，用自己的手巾像对待小孩子一样仔细地为鹤见副部长擦去额头上的汗。到现在为止……我所属的时候没有的情景。",
    "checked": 0
  },
  {
    "old": "喉が渇かないか。すぐに持ってくるから。",
    "new": "口渴吗？我马上就拿来。",
    "checked": 0
  },
  {
    "old": "Vo_miy_0035",
    "new": "Vo_miy_0035"
  },
  {
    "old": "お姫様にするようにかいがいしく尽くす宮原部長。凛々しくもさっぱりした気性だから、鶴見副部長と付き合うようになっても“自分に付いてこい”というタイプだと思ったのだけど。",
    "new": "宫原部长像对待公主一样尽心尽力。因为是凛然爽快的性格，所以即使和鹤见副部长交往，我也觉得她是那种“跟着自己走”的类型。",
    "checked": 0
  },
  {
    "old": "ST_TR_21_0E",
    "new": "ST_TR_21_0E"
  },
  {
    "old": "そんなに慌てなくても大丈夫よ。もう、ふふっ。",
    "new": "你不用那么慌张。已经，呵呵。",
    "checked": 0
  },
  {
    "old": "Vo_tur_0029",
    "new": "Vo_tur_0029"
  },
  {
    "old": "幸せそうに微笑む。秋だというのにそこに春が訪れたように。",
    "new": "幸福地微笑着。虽说是秋天，但春天却来到了那里。",
    "checked": 0
  },
  {
    "old": "部員皆、付き合っているのは察しているけれど誰も口には出さないようにしているのだという。",
    "new": "虽然我知道部员们都在交往，但是谁也不会说出口。",
    "checked": 0
  },
  {
    "old": "堅物な宮原部長は二人が交際している事を打ち明けたら公私混同は許さずと、今のような微笑ましい光景は見られないだろうからと。",
    "new": "严肃的宫原部长说，如果把两人交往的事情说出来，就不允许公私混淆，不会再看到像现在这样令人欣慰的光景了。",
    "checked": 0
  },
  {
    "old": "ST_MY_21_2E",
    "new": "ST_MY_21_2E"
  },
  {
    "old": "すまない。スポーツドリンクしかないんだけれどいいかな。",
    "new": "对不起。只有运动饮料，可以吗？",
    "checked": 0
  },
  {
    "old": "Vo_miy_0036",
    "new": "Vo_miy_0036"
  },
  {
    "old": "葵が持ってきてくれたものがいいの。",
    "new": "葵给我带来的东西比较好。",
    "checked": 0
  },
  {
    "old": "Vo_tur_0030",
    "new": "Vo_tur_0030"
  },
  {
    "old": "秋に訪れた春。小さいけれど確かな変化。",
    "new": "秋天到来的春天。虽然很小但是确实的变化。",
    "checked": 0
  },
  {
    "old": "そして、ふたつ目の変化は――",
    "new": "然后，第二个变化是——",
    "checked": 0
  },
  {
    "old": "eye004",
    "new": "eye004"
  },
  {
    "old": "bg004_1",
    "new": "bg004_1"
  },
  {
    "old": "新しい友人となった木野ゆり香。",
    "new": "成为新朋友的木野百合香。",
    "checked": 0
  },
  {
    "old": "彼女とは合唱会を機にかかわり、一度は仲違いしたけれども――宝珠先輩のお陰で友人となることができた。",
    "new": "我和她因为合唱会的关系，一度不和——但多亏宝珠前辈，我们才得以成为朋友。",
    "checked": 0
  },
  {
    "old": "木野さんは合唱会に披露した見事なピアノを――ではなく、数合わせとしてあまり興味のなかった茶道部に籍を置いて貰ったけれど、その茶道に魅せられたらしい。",
    "new": "木野同学在合唱会上表演了漂亮的钢琴——并不是——而是在作为数组不太感兴趣的茶道部放了籍，但是好像被那个茶道所吸引。",
    "checked": 0
  },
  {
    "old": "bg001",
    "new": "bg001"
  },
  {
    "old": "ST_KN_01_0A",
    "new": "ST_KN_01_0A"
  },
  {
    "old": "木野",
    "new": "木野",
    "checked": 0
  },
  {
    "old": "部長。茶筅で抹茶を練るときどうやったらもっと上手くできるでしょうか？",
    "new": "部长。用茶筅刷抹茶的时候，怎样才能做得更好呢？",
    "checked": 0
  },
  {
    "old": "Vo_kin_0081",
    "new": "Vo_kin_0081"
  },
  {
    "old": "そう、部活動では一番宝珠先輩へ質問し実践していった。初期メンバーだったわたしやメイよりも熱心で、今では宝珠先輩が一番目を掛けているくらいに。",
    "new": "是的，在社团活动中，我向最宝珠前辈提问并实践。比初期成员的我和小明更热心，现在宝珠前辈最引人注目了。",
    "checked": 0
  },
  {
    "old": "ST_KN_01_0B",
    "new": "ST_KN_01_0B"
  },
  {
    "old": "佐和良義流に口を利いて貰ってありがとうございます。",
    "new": "谢谢佐和良义流帮我说话。",
    "checked": 0
  },
  {
    "old": "Vo_kin_0082",
    "new": "Vo_kin_0082"
  },
  {
    "old": "更にもっと腕を磨こうと宝珠先輩に頼み込み佐和良義流の門下生――練習生になったとのこと。",
    "new": "为了进一步磨炼自己的手艺，她央求宝珠前辈成为佐和良义流的门生——练习生。",
    "checked": 0
  },
  {
    "old": "クラスでは茶道教室のことを話してくれるようになった。今となっては気の置けない友人の一人だ。",
    "new": "在班上，我开始谈论茶道教室的事情了。时至今日，她是我没有隔阂的朋友之一。",
    "checked": 0
  },
  {
    "old": "そして、",
    "new": "然后，",
    "checked": 0
  },
  {
    "old": "bg007",
    "new": "bg007"
  },
  {
    "old": "気の置けない友人といえば、春日恵理。",
    "new": "说到不可在意的朋友，春日惠理。",
    "checked": 0
  },
  {
    "old": "三つ目の変化として挙げたいところだけど……恵理ちゃんに関しては特に変化らしい変化はない。",
    "new": "我想列举第三个变化……关于惠理没有什么特别变化。",
    "checked": 0
  },
  {
    "old": "いつも通り登校すると一番に話し掛けてくれて、体育や化学の授業で組まなくちゃいけないときは率先して手を挙げてくれる友人だ。",
    "new": "和往常一样上学的话会第一个跟我说话，在体育和化学课上必须要组织的时候，是率先举手的朋友。",
    "checked": 0
  },
  {
    "old": "変化がないというと怠惰や勤勉ではないと取られそうだけれど、そこがすごいところでもある。それは変わらぬ自分を持っているということだから。",
    "new": "如果说没有变化的话，可能会被认为不是懒惰和勤奋，但这也是一个很厉害的地方。因为那是因为拥有不变的自己。",
    "checked": 0
  },
  {
    "old": "初秋から友人になった彼女だけど、今思えば入学してすぐに色々と話し掛けてくれたのを思い出す。ただ、あの頃はメイが居てくれればいいと自分に壁を作っていたと思う。",
    "new": "虽然她从初秋开始就成为了朋友，但是现在回想起来，入学后马上就跟我聊了很多话。只是，那个时候，我觉得只要小明在就好了，给自己筑起了一堵墙。",
    "checked": 0
  },
  {
    "old": "だから、クラスメイトではあっても友人にはなり得なかった。",
    "new": "所以，即使是同班同学也不能成为朋友。",
    "checked": 0
  },
  {
    "old": "メイの冤罪事件があって、余裕がなかったわたしへ気に掛けてくれて色々と話すようになってから親密になれたと思う。",
    "new": "因为小明的冤案，我没有时间，她很在意我，跟我说了很多话，我想她是在那之后才变得亲密起来的。",
    "checked": 0
  },
  {
    "old": "朗らかでクラス皆から愛されている友人。",
    "new": "性格开朗，深受同学喜爱的朋友。",
    "checked": 0
  },
  {
    "old": "ST_KS_01_0B",
    "new": "ST_KS_01_0B"
  },
  {
    "old": "恵理",
    "new": "惠理",
    "checked": 0
  },
  {
    "old": "駅前に美味しいスープカレーのお店見付けたんだ。行こうよアリス。",
    "new": "我在车站前发现了一家好吃的咖喱汤店。去吧爱丽丝。",
    "checked": 0
  },
  {
    "old": "Vo_kas_0124",
    "new": "Vo_kas_0124"
  },
  {
    "old": "ほとんど毎日、学校帰りの買い食いを誘ってくるのは閉口ものだけど。それと、",
    "new": "几乎每天都邀请从学校回来的人买东西吃是闭口无言的。还有，",
    "checked": 0
  },
  {
    "old": "ST_KS_01_0E",
    "new": "ST_KS_01_0E"
  },
  {
    "old": "あ、もちろんメイも誘ったよ！",
    "new": "啊，当然我也邀请了小明哦！",
    "checked": 0
  },
  {
    "old": "Vo_kas_0125",
    "new": "Vo_kas_0125"
  },
  {
    "old": "幼馴染みと仲良くなり過ぎなところは、少し嫉妬してしまっているけれど。",
    "new": "和儿时玩伴关系太好的地方，虽然有点嫉妒。",
    "checked": 0
  },
  {
    "old": "そう、",
    "new": "对，",
    "checked": 0
  },
  {
    "old": "嫉妬してしまうほどに大切にしている親友。",
    "new": "珍惜得让人嫉妒的好朋友。",
    "checked": 0
  },
  {
    "old": "穂高明との関わりは――当たり前のように変化していくことになった。３つ目の悩ましい変化。",
    "new": "和穗高明的关系——变得理所当然地发生了变化。第三个令人烦恼的变化。",
    "checked": 0
  },
  {
    "old": "bgm04",
    "new": "bgm04"
  },
  {
    "old": "宝珠先輩と交際すると決めた次の日。",
    "new": "决定和宝珠前辈交往的第二天。",
    "checked": 0
  },
  {
    "old": "多幸感とともにしなければいけないこと――穂高明に佐和良義宝珠と交際し始めたことを告白しなくてはいけないと心に決めたのだ。",
    "new": "我下定决心，必须和多幸感一起做的事——必须向穗高明告白和佐和良义宝珠开始交往的事情。",
    "checked": 0
  },
  {
    "old": "それもなるべく早く。",
    "new": "那个也尽量早点。",
    "checked": 0
  },
  {
    "old": "こういった話は後に延ばせば延ばすほど誤解からの軋轢を生むのが常だし、わたしがメイならやっぱり……早く教えてほしいと思う。",
    "new": "这种事越往后拖，越容易引起误会，如果我是小明的话……我想早点告诉我。",
    "checked": 0
  },
  {
    "old": "bg008_2",
    "new": "bg008_2"
  },
  {
    "old": "だからわたしは、朝の登校で。",
    "new": "所以我早上上学的时候。",
    "checked": 0
  },
  {
    "old": "満員の電車の中で。",
    "new": "在拥挤的电车里。",
    "checked": 0
  },
  {
    "old": "混雑するバスの中で。",
    "new": "在拥挤的巴士里。",
    "checked": 0
  },
  {
    "old": "かしましい声でいっぱいの廊下で。",
    "new": "在充满悲鸣的走廊里。",
    "checked": 0
  },
  {
    "old": "お昼休みの食堂、体育の合間など折を見付け話そうと思ったのだけど――",
    "new": "本想找个午休的食堂、体育课的空当和你聊聊的——",
    "checked": 0
  },
  {
    "old": "ST_AL_02_0D",
    "new": "ST_AL_02_0D"
  },
  {
    "old": "アリス",
    "new": "爱丽丝",
    "checked": 0
  },
  {
    "old": "『……話し掛ける勇気がでない！』",
    "new": "“……没有勇气搭话！”",
    "checked": 0
  },
  {
    "old": "Vo_alc_0607",
    "new": "Vo_alc_0607"
  },
  {
    "old": "幾つかチャンスはあったのだけど、声を掛ける勇気はでなかった。朗らかなメイを前にすると声が消え失せてしまうのだ。",
    "new": "虽然有几个机会，但我没有勇气去搭讪。在开朗的小明面前，声音就消失了。",
    "checked": 0
  },
  {
    "old": "早く伝えなきゃと心に決めた日から七日が過ぎてしまった……。",
    "new": "从下定决心要尽快传达的那天起，已经过去七天了……。",
    "checked": 0
  },
  {
    "old": "それは――宝珠先輩との交際を彼女に伝えたことに対する変化を危惧してのことだ。",
    "new": "那是——担心她对向她传达和宝珠前辈交往的变化。",
    "checked": 0
  },
  {
    "old": "元々、宝珠先輩を気に入っていたメイからすればわたしを裏切り者だと思うかもしれない。大切にしていたものを奪っていった者だと。",
    "new": "原本，对于喜欢宝珠前辈的小明来说，也许会觉得我是背叛者。是夺走了自己珍视的东西的人。",
    "checked": 0
  },
  {
    "old": "怒りの目でメイに睨まれるのを考えただけで身体が竦む。",
    "new": "只是想用愤怒的眼睛被小明盯着身体就缩影了。",
    "checked": 0
  },
  {
    "old": "佐和良義宝珠はかけがえない人だけれど、穂高明もわたしにとって代えようのない大切な人なのだ。",
    "new": "佐和良义宝珠是无可替代的人，穗高明对我来说也是无可替代的重要的人。",
    "checked": 0
  },
  {
    "old": "だから――……",
    "new": "所以——……",
    "checked": 0
  },
  {
    "old": "ST_ME_01_1E",
    "new": "ST_ME_01_1E"
  },
  {
    "old": "メイ",
    "new": "小明",
    "checked": 0
  },
  {
    "old": "何かあたしへ話したい事があるんでしょ？",
    "new": "你有什么话想对我说吧？",
    "checked": 0
  },
  {
    "old": "Vo_may_0281",
    "new": "Vo_may_0281"
  },
  {
    "old": "bg006_1",
    "new": "bg006_1"
  },
  {
    "old": "ST_ME_03_1E",
    "new": "ST_ME_03_1E"
  },
  {
    "old": "でしょ、アリス。",
    "new": "对吧，爱丽丝。",
    "checked": 0
  },
  {
    "old": "Vo_may_0282",
    "new": "Vo_may_0282"
  },
  {
    "old": "部活終わり、帰路につこうと校庭を横切っていく途中で、メイがそう切り出したのだ。",
    "new": "社团活动结束后，在横穿校园准备回家的途中，小明开口了。",
    "checked": 0
  },
  {
    "old": "幼馴染みのまなざしは柔らかで、真摯に問い掛けていた。わたしは、",
    "new": "儿时好友的目光柔和而真挚地问道。我呢，",
    "checked": 0
  },
  {
    "old": "ST_AL_02_1G",
    "new": "ST_AL_02_1G"
  },
  {
    "old": "『……話していいの？　本当に？』",
    "new": "“……可以说话吗？真的吗？”",
    "checked": 0
  },
  {
    "old": "Vo_alc_0608",
    "new": "Vo_alc_0608"
  },
  {
    "old": "ずっと迷い悩んでいたことが浮かぶ。本当に穂高明へ、宝珠先輩と交際を始めたことを伝えていいのか。",
    "new": "一直犹豫烦恼的事情浮现在眼前。真的可以告诉穗高明和宝珠前辈开始交往吗？",
    "checked": 0
  },
  {
    "old": "それを話した途端、わたしとメイの繋がりは今とは違ったものに……最悪、断ち切られてしまうのではないか？",
    "new": "刚说了那个，我和小明的联系就变成了和现在不一样的东西……最坏的是，不是被切断了呢？",
    "checked": 0
  },
  {
    "old": "ST_AL_02_1A",
    "new": "ST_AL_02_1A"
  },
  {
    "old": "ぁ、実は……。",
    "new": "啊，其实……。",
    "checked": 0
  },
  {
    "old": "Vo_alc_0609",
    "new": "Vo_alc_0609"
  },
  {
    "old": "後味の悪い映画を観て、と言おうとした刹那、メイの瞳を目にして何も言えなくなってしまった。",
    "new": "就在我想说“看了一部让人不舒服的电影”的刹那，看到小明的眼睛，我什么都说不出来了。",
    "checked": 0
  },
  {
    "old": "わたしへ常に正直で優しい親友へ嘘を吐くのかと。",
    "new": "对一向对我正直温柔的好朋友说谎吗？",
    "checked": 0
  },
  {
    "old": "わたしは――お腹に力を入れ、拳を握り締め、口を開いた。",
    "new": "我——腹部用力，握紧拳头，开口。",
    "checked": 0
  },
  {
    "old": "ST_AL_02_0H",
    "new": "ST_AL_02_0H"
  },
  {
    "old": "あ、あのね……。実は……。",
    "new": "啊，那个……。其实……。",
    "checked": 0
  },
  {
    "old": "Vo_alc_0610",
    "new": "Vo_alc_0610"
  },
  {
    "old": "ST_ME_03_0A",
    "new": "ST_ME_03_0A"
  },
  {
    "old": "うん？",
    "new": "嗯？",
    "checked": 0
  },
  {
    "old": "Vo_may_0283",
    "new": "Vo_may_0283"
  },
  {
    "old": "言葉ではない何か別のものが迫りあがりそうになりながら、",
    "new": "不是语言的其他东西好像要逼近了，",
    "checked": 0
  },
  {
    "old": "ST_AL_03_0I",
    "new": "ST_AL_03_0I"
  },
  {
    "old": "宝珠……先輩と、交際することに……なったの……。",
    "new": "宝珠……和前辈交往……变成了……。",
    "checked": 0
  },
  {
    "old": "Vo_alc_0611",
    "new": "Vo_alc_0611"
  },
  {
    "old": "と、ようやく言葉にすることができた。",
    "new": "终于可以用语言来表达了。",
    "checked": 0
  },
  {
    "old": "ST_ME_02_1A",
    "new": "ST_ME_02_1A"
  },
  {
    "old": "え……？　交際って、付き合うってことだよね？",
    "new": "诶……？交际，就是交际吧？",
    "checked": 0
  },
  {
    "old": "Vo_may_0284",
    "new": "Vo_may_0284"
  },
  {
    "old": "ST_AL_03_0D",
    "new": "ST_AL_03_0D"
  },
  {
    "old": "う、うん……。",
    "new": "嗯，嗯……。",
    "checked": 0
  },
  {
    "old": "Vo_alc_0612",
    "new": "Vo_alc_0612"
  },
  {
    "old": "おずおずと見詰める視線は……視線を合わせることはできなかった。",
    "new": "毫不犹豫地凝视着的视线……我没能对视。",
    "checked": 0
  },
  {
    "old": "メイは、顔を伏せてしまっていたのだ。そして、ただ黙って芝生を見下ろすだけ。",
    "new": "小明趴在了脸上。然后，只是默默地俯视草坪而已。",
    "checked": 0
  },
  {
    "old": "『…………ッ』",
    "new": "“…………月色”",
    "checked": 0
  },
  {
    "old": "Vo_alc_0613",
    "new": "Vo_alc_0613"
  },
  {
    "old": "心の中で激しく黒い感情の渦がうねり、たまらず胸に手を当てた。",
    "new": "心中强烈的黑色感情的漩涡翻滚，手贴在了胸口。",
    "checked": 0
  },
  {
    "old": "胸の、腹の中を後悔が巡り、立っているのもままならない。と、",
    "new": "心中的、心中充满了后悔，站着也不如意。这时，",
    "checked": 0
  },
  {
    "old": "SE_052",
    "new": "SE_052"
  },
  {
    "old": "ST_ME_01_0E_L",
    "new": "ST_ME_01_0E_L"
  },
  {
    "old": "え。",
    "new": "呃。",
    "checked": 0
  },
  {
    "old": "Vo_alc_0614",
    "new": "Vo_alc_0614"
  },
  {
    "old": "ST_ME_01_0I_L",
    "new": "ST_ME_01_0I_L"
  },
  {
    "old": "不意に抱きしめられ当惑する。否、抱きしめたメイの背中が[n]{戦慄/わなな}いているのを見て、さっきよりも強く心臓を掴まれた。",
    "new": "被突然拥抱而困惑。不，拥抱着的小明的背影[n]看到她战栗的样子，心脏比刚才更用力地被抓住了。",
    "checked": 0
  },
  {
    "old": "ST_ME_01_0B_L",
    "new": "ST_ME_01_0B_L"
  },
  {
    "old": "おめでとう、アリス！",
    "new": "恭喜你，爱丽丝！",
    "checked": 0
  },
  {
    "old": "Vo_may_0285",
    "new": "Vo_may_0285"
  },
  {
    "old": "え？　え？",
    "new": "诶？诶？",
    "checked": 0
  },
  {
    "old": "Vo_alc_0615",
    "new": "Vo_alc_0615"
  },
  {
    "old": "そうなんじゃないかって思ってたんだけど、やっぱりそうだったんだね！　やったねアリス！",
    "new": "我还以为是这样，果然是这样啊！太好了爱丽丝！",
    "checked": 0
  },
  {
    "old": "Vo_may_0286",
    "new": "Vo_may_0286"
  },
  {
    "old": "メイの表情は笑顔で……声も弾んでいて……訳が分からず顔を凝っと見詰めてしまう。と、また強く抱きしめてくれた。",
    "new": "小明的表情是笑容……声音也很激动……莫名其妙地凝视着脸。然后，又紧紧地抱住了我。",
    "checked": 0
  },
  {
    "old": "アリスが佐和良義先輩を好きだって気がしてたから、上手くいくといいなって思ってたんだ。だから良かったよ！",
    "new": "因为觉得爱丽丝喜欢佐和良义前辈，所以我觉得顺利就好了。所以太好了！",
    "checked": 0
  },
  {
    "old": "Vo_may_0287",
    "new": "Vo_may_0287"
  },
  {
    "old": "あ、あの……怒ってないの？",
    "new": "啊，那个……你没有生气吗？",
    "checked": 0
  },
  {
    "old": "Vo_alc_0616",
    "new": "Vo_alc_0616"
  },
  {
    "old": "ST_ME_01_1A_L",
    "new": "ST_ME_01_1A_L"
  },
  {
    "old": "え？　何で？　あたしが？",
    "new": "诶？为什么？我？",
    "checked": 0
  },
  {
    "old": "Vo_may_0288",
    "new": "Vo_may_0288"
  },
  {
    "old": "だって、その、メイ、宝珠先輩を好き……だったでしょ？",
    "new": "因为，那个小明喜欢宝珠前辈……是吧？",
    "checked": 0
  },
  {
    "old": "Vo_alc_0617",
    "new": "Vo_alc_0617"
  },
  {
    "old": "ST_ME_03_2E_L",
    "new": "ST_ME_03_2E_L"
  },
  {
    "old": "ST_ME_03_1G_L",
    "new": "ST_ME_03_1G_L"
  },
  {
    "old": "わたしの言葉に目をパチパチとさせ、次いで破顔してみせた。",
    "new": "听了我的话，她眨巴着眼睛，接着露出了笑容。",
    "checked": 0
  },
  {
    "old": "ああ！　好きだって言ってたっけ？　でも、あの好きはちょっと違くて……好きな俳優とか歌手に対する憧れみたいなやつだよ。",
    "new": "啊！你说过喜欢吗？但是，那种喜欢有点不一样……是喜欢的演员和对歌手的憧憬一样的东西。",
    "checked": 0
  },
  {
    "old": "Vo_may_0289",
    "new": "Vo_may_0289"
  },
  {
    "old": "ST_ME_01_1E_L",
    "new": "ST_ME_01_1E_L"
  },
  {
    "old": "あたしにはないものを佐和良義先輩はたくさん持ってたから。",
    "new": "因为佐和良义前辈有很多我没有的东西。",
    "checked": 0
  },
  {
    "old": "Vo_may_0290",
    "new": "Vo_may_0290"
  },
  {
    "old": "そう……なの？",
    "new": "是吗……是吗？",
    "checked": 0
  },
  {
    "old": "Vo_alc_0618",
    "new": "Vo_alc_0618"
  },
  {
    "old": "ST_ME_01_0F_L",
    "new": "ST_ME_01_0F_L"
  },
  {
    "old": "うん。あ、最近ずっと妙だったのはそのことを気にしてたからか！　何か話したそうだなって思ってたけど、黙ってるし無理やり聞くのもなぁって思って――。",
    "new": "嗯。啊，最近一直很奇怪是因为很在意这件事吧！虽然觉得好像说了什么，但是我觉得沉默也不要勉强问。",
    "checked": 0
  },
  {
    "old": "Vo_may_0291",
    "new": "Vo_may_0291"
  },
  {
    "old": "ST_ME_01_2E_L",
    "new": "ST_ME_01_2E_L"
  },
  {
    "old": "七日も変わらなかったしさすがに聞いたんだ、と言った。",
    "new": "她说，七天没变，不愧是听说了。",
    "checked": 0
  },
  {
    "old": "そうだったの……。",
    "new": "原来是这样……。",
    "checked": 0
  },
  {
    "old": "Vo_alc_0619",
    "new": "Vo_alc_0619"
  },
  {
    "old": "一番の気掛かりがなくなり、気が抜けてしまった。ふらつくわたしの背に手を回し立たせてくれる。",
    "new": "没有了最担心的地方，心情也不好了。我的背上转动着我的手站着。",
    "checked": 0
  },
  {
    "old": "そんなに気掛かりだったなんてごめん。早く聞いたらよかったね。",
    "new": "那么担心，对不起。要是早点问就好了。",
    "checked": 0
  },
  {
    "old": "Vo_may_0292",
    "new": "Vo_may_0292"
  },
  {
    "old": "ST_AL_02_2E",
    "new": "ST_AL_02_2E"
  },
  {
    "old": "ううん。わたしも早くメイへ言えば良かった。",
    "new": "没有。我也早点对小明说就好了。",
    "checked": 0
  },
  {
    "old": "Vo_alc_0620",
    "new": "Vo_alc_0620"
  },
  {
    "old": "メイの本心を知った今はそう言える。でも、俯いて戦慄いた背中を目にしたときの感情もまた確かだった。",
    "new": "现在知道了小明的真心，可以这么说。但是，看到她低着头战栗的背影时的感情也是真切的。",
    "checked": 0
  },
  {
    "old": "それでどっちが告白したの？　好きだって。",
    "new": "那么谁告白了？说喜欢。",
    "checked": 0
  },
  {
    "old": "Vo_may_0293",
    "new": "Vo_may_0293"
  },
  {
    "old": "え？　そ、それは……。",
    "new": "诶？那、那是……。",
    "checked": 0
  },
  {
    "old": "Vo_alc_0621",
    "new": "Vo_alc_0621"
  },
  {
    "old": "ST_ME_03_0B_L",
    "new": "ST_ME_03_0B_L"
  },
  {
    "old": "照れてる。",
    "new": "害羞。",
    "checked": 0
  },
  {
    "old": "Vo_may_0294",
    "new": "Vo_may_0294"
  },
  {
    "old": "ST_AL_03_0C",
    "new": "ST_AL_03_0C"
  },
  {
    "old": "笑うメイへ、もう！　と抗議すると、抱きしめていた手をわたしの顔に当て、",
    "new": "对笑小明，够了！抗议的时候，把抱着的手贴在我的脸上，",
    "checked": 0
  },
  {
    "old": "ST_ME_02_1E_L",
    "new": "ST_ME_02_1E_L"
  },
  {
    "old": "アリス、顔を見せて。",
    "new": "爱丽丝，给我看你的脸。",
    "checked": 0
  },
  {
    "old": "Vo_may_0295",
    "new": "Vo_may_0295"
  },
  {
    "old": "そう言い、凝っとわたしの顔を見詰めたのだ。",
    "new": "这样说着，凝望着我的脸。",
    "checked": 0
  },
  {
    "old": "え、どうしたの、急に？",
    "new": "啊，怎么了，突然？",
    "checked": 0
  },
  {
    "old": "Vo_alc_0622",
    "new": "Vo_alc_0622"
  },
  {
    "old": "身体がかっと熱くなり、頬に、顔に血が上ってくるのが分かる。変な顔をしてないか不安で顔を伏せたくなる。",
    "new": "我感到身体一下子热了起来，脸颊和脸上涌上了血。担心会不会有奇怪的表情，想低下头。",
    "checked": 0
  },
  {
    "old": "ST_ME_02_0B_L",
    "new": "ST_ME_02_0B_L"
  },
  {
    "old": "恋をすると綺麗になるって言うだろ。本当だ。すごく綺麗になった。",
    "new": "不是说恋爱会变漂亮吗？是真的。变得非常漂亮了。",
    "checked": 0
  },
  {
    "old": "Vo_may_0296",
    "new": "Vo_may_0296"
  },
  {
    "old": "言い、わたしの顔から手を離し、両の手で自分のポケットをさぐった。どうしたの？　と声を掛けると、",
    "new": "说了，手从我的脸上放开，用双手摸了自己的口袋。怎么了？这样打招呼的话，",
    "checked": 0
  },
  {
    "old": "目を奪われた。綺麗だよアリス。",
    "new": "我被吸引住了目光。爱丽丝很漂亮。",
    "checked": 0
  },
  {
    "old": "Vo_may_0297",
    "new": "Vo_may_0297"
  },
  {
    "old": "メイの言葉に嬉しさがこみ上げ多幸感が身体を巡る。けれど、その声に別れを予感する響きがあり、背が薄くなるような儚い気持ちになる。",
    "new": "对于小明的话，喜悦感涌上心头，幸福感围绕着身体。但是，那个声音有预感分手的声音，变成了背变薄一样的虚幻的心情。",
    "checked": 0
  },
  {
    "old": "ありがとうメイ。ねぇ……わたしたちずっと一緒よね？",
    "new": "谢谢你。哎……我们会一直在一起吧？",
    "checked": 0
  },
  {
    "old": "Vo_alc_0623",
    "new": "Vo_alc_0623"
  },
  {
    "old": "ああ、もちろんだよ。あたしがそう問いたかった。あたしを親友のままでいさせてくれって。",
    "new": "啊，当然了。我想这么问。让我保持好朋友的状态。",
    "checked": 0
  },
  {
    "old": "Vo_may_0298",
    "new": "Vo_may_0298"
  },
  {
    "old": "メイはずっとわたしの親友だよ！　それは変わることはない！",
    "new": "小明一直是我的好朋友哦！那是不会改变的！",
    "checked": 0
  },
  {
    "old": "Vo_alc_0624",
    "new": "Vo_alc_0624"
  },
  {
    "old": "ST_ME_02_0I_L",
    "new": "ST_ME_02_0I_L"
  },
  {
    "old": "よかった……。佐和良義先輩と交際するのは喜ばしいけど、親友が遠くに行ってしまう気がして……。",
    "new": "太好了……。虽然和佐和良义前辈交往很开心，但是感觉好朋友会去很远的地方……。",
    "checked": 0
  },
  {
    "old": "Vo_may_0299",
    "new": "Vo_may_0299"
  },
  {
    "old": "あたしより、仲がいい人ができるのは……ちょっと、ううん、嫌な気持ちになっちゃったんだ……。",
    "new": "能有比我关系更好的人……有点，不，我有点讨厌……。",
    "checked": 0
  },
  {
    "old": "Vo_may_0300",
    "new": "Vo_may_0300"
  },
  {
    "old": "大切な人に、友だちに順番は付けられないというけれど、子供の頃から……わたしを救ってくれたヒーローだったメイはどんなことがあっても変わらぬ大切な人だ。",
    "new": "虽说重要的人、朋友不能按顺序排列，但从小就……救了我的英雄小明是无论发生什么事都不会改变的重要的人。",
    "checked": 0
  },
  {
    "old": "だから順位は――……",
    "new": "所以排名是——……",
    "checked": 0
  },
  {
    "old": "ST_AL_02_0B",
    "new": "ST_AL_02_0B"
  },
  {
    "old": "わたしにとっての一番の親友はメイだよ。",
    "new": "对我来说最好的朋友是小明。",
    "checked": 0
  },
  {
    "old": "Vo_alc_0625",
    "new": "Vo_alc_0625"
  },
  {
    "old": "そうだね……。ふふっお互い知られたらマズイ恥ずかしいこともたくさん知ってるし。",
    "new": "是啊……。我知道很多如果互相知道了就不好意思了的事情。",
    "checked": 0
  },
  {
    "old": "Vo_may_0301",
    "new": "Vo_may_0301"
  },
  {
    "old": "{戯/おど}けるメイへ確かにそうだと笑顔を作る。わたしにとって大切な人。それに変わりはない。",
    "new": "对开玩笑的小明确实是这样笑着。对我来说很重要的人。这一点没有改变。",
    "checked": 0
  },
  {
    "old": "『ぁ……』",
    "new": "“啊……”",
    "checked": 0
  },
  {
    "old": "Vo_alc_0626",
    "new": "Vo_alc_0626"
  },
  {
    "old": "ふっと宝珠先輩の柔らかな微笑みが浮かんだ。同じくらいに大切な人。",
    "new": "宝珠前辈温柔的微笑突然浮现在眼前。同样重要的人。",
    "checked": 0
  },
  {
    "old": "今、佐和良義先輩のこと考えてただろ？",
    "new": "你现在不是在想佐和良义前辈吗？",
    "checked": 0
  },
  {
    "old": "Vo_may_0302",
    "new": "Vo_may_0302"
  },
  {
    "old": "え？",
    "new": "诶？",
    "checked": 0
  },
  {
    "old": "Vo_alc_0627",
    "new": "Vo_alc_0627"
  },
  {
    "old": "何で分かったのって顔してるけど親友のあたしにはお見通しだよ。アリス、佐和良義先輩に会いに行った方がいい。",
    "new": "你一副怎么知道的表情，我这个好朋友早就看穿了。爱丽丝，去见佐和良义前辈比较好。",
    "checked": 0
  },
  {
    "old": "Vo_may_0303",
    "new": "Vo_may_0303"
  },
  {
    "old": "言い、頭を、髪をゆっくりと撫で、子供へ言い聞かせるように言った。",
    "new": "说了，慢慢地抚摸着头，让孩子听。",
    "checked": 0
  },
  {
    "old": "ずっとあたしのことが気掛かりで、佐和良義先輩と付き合ってても向き合えてなかっただろ？　親友に祝福して貰ったって話してきたらいい。",
    "new": "一直都很担心我，即使和佐和良义前辈交往也没能面对吧？你可以告诉我朋友祝福我。",
    "checked": 0
  },
  {
    "old": "Vo_may_0304",
    "new": "Vo_may_0304"
  },
  {
    "old": "……[#]……。",
    "new": "……[#]……。",
    "checked": 0
  },
  {
    "old": "Vo_alc_0628",
    "new": "Vo_alc_0628"
  },
  {
    "old": "ST_ME_03_1E_L",
    "new": "ST_ME_03_1E_L"
  },
  {
    "old": "アリスはあたしをずっと一番にしてくれていた。でも、一番はふたつ有ったっていいんだ。一番が多い方が幸せだろ？",
    "new": "爱丽丝一直把我放在第一位。不过，有两个第一也没关系。最多的一方会幸福吧？",
    "checked": 0
  },
  {
    "old": "Vo_may_0305",
    "new": "Vo_may_0305"
  },
  {
    "old": "そうなのかな……？",
    "new": "是吗……？",
    "checked": 0
  },
  {
    "old": "Vo_alc_0629",
    "new": "Vo_alc_0629"
  },
  {
    "old": "あたしの一番はアリスで――もうひとつの一番は母や兄たち。それと親父が作るカレーも捨て難い。",
    "new": "我的第一是爱丽丝——另一个第一是母亲和哥哥们。还有父亲做的咖喱也很难扔掉。",
    "checked": 0
  },
  {
    "old": "Vo_may_0306",
    "new": "Vo_may_0306"
  },
  {
    "old": "ST_AL_02_0I",
    "new": "ST_AL_02_0I"
  },
  {
    "old": "冗談で笑わせてくれるけれど、鼻の奥がツンとしてしまった。",
    "new": "虽然开玩笑逗我笑，但是鼻子深处却很傲娇。",
    "checked": 0
  },
  {
    "old": "だから行ってこい。祝福するよ。アリス。",
    "new": "所以你去吧。我会祝福你的。爱丽丝。",
    "checked": 0
  },
  {
    "old": "Vo_may_0307",
    "new": "Vo_may_0307"
  },
  {
    "old": "ST_AL_01_0B",
    "new": "ST_AL_01_0B"
  },
  {
    "old": "うん。ありがとうメイ。",
    "new": "嗯。谢谢你。",
    "checked": 0
  },
  {
    "old": "Vo_alc_0630",
    "new": "Vo_alc_0630"
  },
  {
    "old": "ST_AL_02_1E",
    "new": "ST_AL_02_1E"
  },
  {
    "old": "ST_ME_02_1E",
    "new": "ST_ME_02_1E"
  },
  {
    "old": "身体を離し、肩に手を当て言い聞かせるよう腕を叩いた。",
    "new": "放开身体，用手捂着肩膀听她说话，拍了胳膊。",
    "checked": 0
  },
  {
    "old": "わたしは頷き、目で答えると踵を返し、グランドを駆けていった。",
    "new": "我点点头，用眼神回答后，转身跑向运动场。",
    "checked": 0
  },
  {
    "old": "SE_053",
    "new": "SE_053"
  },
  {
    "old": "彼女の元へ。",
    "new": "去她身边。",
    "checked": 0
  },
  {
    "old": "ST_ME_01_0I",
    "new": "ST_ME_01_0I"
  },
  {
    "old": "……[#]これでいい。だよな、アリス。",
    "new": "……[#]这样就可以了。所以呢，爱丽丝。",
    "checked": 0
  },
  {
    "old": "Vo_may_0308",
    "new": "Vo_may_0308"
  },
  {
    "old": "胸の中に、否、体中に伝えなくちゃいけないという気持ちが駆け巡っていた。",
    "new": "胸中，不，必须传达给全身的心情盘旋着。",
    "checked": 0
  },
  {
    "old": "それは多幸感であり、切迫感であり、衝動であった。",
    "new": "那是一种幸福感、紧迫感和冲动。",
    "checked": 0
  },
  {
    "old": "bg001_1",
    "new": "bg001_1"
  },
  {
    "old": "SE_017",
    "new": "SE_017"
  },
  {
    "old": "佐和良義宝珠がもう帰っているかもなんて考えは浮かびもしなかった。",
    "new": "完全没有想到佐和良义宝珠可能已经回来了。",
    "checked": 0
  },
  {
    "old": "ST_HO_11_1A",
    "new": "ST_HO_11_1A"
  },
  {
    "old": "襖を荒々しく開けたわたしへ驚いた顔で見上げた宝珠先輩を目にし、身体を巡っていた感情のほとばしりを口に出したのだ。",
    "new": "看到我粗暴地拉开纸门，宝珠前辈一脸惊讶地抬头望着我，她把围绕身体的情感迸发了出来。",
    "checked": 0
  },
  {
    "old": "FadeSpeedDown",
    "new": "FadeSpeedDown"
  },
  {
    "old": "――穂高明へわたしたちが交際していることを伝えたこと。",
    "new": "——向穗高明传达了我们正在交往的消息。",
    "checked": 0
  },
  {
    "old": "穂高明はすべてを聞き終え、祝福してくれたことを。そして、伝えに行ってこいと背を押されたのだと。",
    "new": "穗高明听完了一切，祝福了我。然后，被推到了背后说要去传达。",
    "checked": 0
  },
  {
    "old": "FadeSpeedUp",
    "new": "FadeSpeedUp"
  },
  {
    "old": "ST_HO_11_1G",
    "new": "ST_HO_11_1G"
  },
  {
    "old": "宝珠",
    "new": "宝珠",
    "checked": 0
  },
  {
    "old": "……[#]そうだったの。",
    "new": "……[#]是吗？",
    "checked": 0
  },
  {
    "old": "Vo_hou_0352",
    "new": "Vo_hou_0352"
  },
  {
    "old": "昂ぶった気持ちをぶつけただけの言葉だった。だから不明瞭で、意図が伝わりにくい部分もあっただろう。",
    "new": "只是发泄了激动的心情。所以才会有模糊不清、难以传达意图的部分。",
    "checked": 0
  },
  {
    "old": "しかし、",
    "new": "但是，",
    "checked": 0
  },
  {
    "old": "ST_HO_13_1B",
    "new": "ST_HO_13_1B"
  },
  {
    "old": "穂高さんが認めてくれた……。",
    "new": "穗高同学承认了……。",
    "checked": 0
  },
  {
    "old": "Vo_hou_0353",
    "new": "Vo_hou_0353"
  },
  {
    "old": "目の端からひとすじの泪の滴が落ちた。",
    "new": "一滴眼泪从眼睛的一端掉下来。",
    "checked": 0
  },
  {
    "old": "彼女の涙を目にして、すべてを理解してくれたのだなと悟った。",
    "new": "看到她的眼泪，我明白了一切都理解了。",
    "checked": 0
  },
  {
    "old": "佐和良義宝珠はわたしと穂高明との心のやり取りを、言葉の意味を、二人が纏う空気を感じ取ったのだなと。",
    "new": "佐和良义宝珠感觉到了我和穗高明之间的对话，感受到了话语的含义，感受到了两人之间的气氛。",
    "checked": 0
  },
  {
    "old": "宝珠先輩は居住まいを正し、わたしへ向き合うと、アリスが伝えたように私も母へ伝えたお話があったの、と切り出した。",
    "new": "宝珠前辈正了正身子，面对着我，开口说，就像爱丽丝说的，我也有话告诉了母亲。",
    "checked": 0
  },
  {
    "old": "ST_HO_11_1E",
    "new": "ST_HO_11_1E"
  },
  {
    "old": "お母さんに……？　もしかして、",
    "new": "对妈妈……？或许，",
    "checked": 0
  },
  {
    "old": "Vo_alc_0631",
    "new": "Vo_alc_0631"
  },
  {
    "old": "ええ。あの幼い頃の……お披露目会でのことを。",
    "new": "嗯。那个小时候的……在发布会上的事。",
    "checked": 0
  },
  {
    "old": "Vo_hou_0354",
    "new": "Vo_hou_0354"
  },
  {
    "old": "ST_AL_03_0A",
    "new": "ST_AL_03_0A"
  },
  {
    "old": "大切なことを話してくれるのだと――気がついた時には、わたしはそっと彼女の手を握っていた。",
    "new": "当我意识到她在对我说重要的事情时，我已经悄悄地握住了她的手。",
    "checked": 0
  },
  {
    "old": "ev010",
    "new": "ev010"
  },
  {
    "old": "宝珠先輩を促すように秋風が背を押し、彼女は唇を開いた。",
    "new": "秋风像是在催促宝珠前辈一样，她张开了嘴唇。",
    "checked": 0
  },
  {
    "old": "ST_HO_11_0D",
    "new": "ST_HO_11_0D"
  },
  {
    "old": "[1]アリスが誤解だと言ってくれたあの日――[5]母へ[7]幼い頃に行ったお披露目会でのことを話したの。",
    "new": "[1]爱丽丝说是误解的那一天——[5]给母亲[7]我说了小时候去的发布会上的事情。",
    "checked": 0
  },
  {
    "old": "Vo_hou_0355",
    "new": "Vo_hou_0355"
  },
  {
    "old": "[1]分家の人たちが発した心ない言葉で動揺したことを、[4]その言葉はただの揶揄ではなく、[6]私の眼には真実だと映ったことを。",
    "new": "[1]分家的人们用无心的语言动摇了，[4]那句话并不是单纯的揶揄，[6]在我眼里是真实的。",
    "checked": 0
  },
  {
    "old": "Vo_hou_0356",
    "new": "Vo_hou_0356"
  },
  {
    "old": "……[#][2]お母さんは？",
    "new": "……[#][2]妈妈呢？",
    "checked": 0
  },
  {
    "old": "Vo_alc_0632",
    "new": "Vo_alc_0632"
  },
  {
    "old": "[1]母は座して[3]私の言葉をただ凝っと訊いていた。[7]瞳を閉じたまま。[9]そして、[11]分家の人たちに言われた言葉より、[13]母が呟いた言葉が[15]私の心を{抉/えぐ}ったのだと話した。",
    "new": "[1]母亲坐下来，[3]只是仔细地听着我的话。[7]闭着眼睛。[9]然后，[11]比起分家人们说的话，[13]母亲嘟囔的话[15]说是剜了我的心。",
    "checked": 0
  },
  {
    "old": "Vo_hou_0357",
    "new": "Vo_hou_0357"
  },
  {
    "old": "“そんな目ならば無ければ良かったのに”",
    "new": "“如果没有那样的眼睛就好了。”",
    "checked": 0
  },
  {
    "old": "[1]そのときに為って[3]ようやく母は瞳を開き[6]私を見詰めた。[8]その眼は当惑しているように見えた。[11]私は、話したの。[13]その言葉が棘となり、[16]楔となり、[17]ずっと自分を縛っていたことを。",
    "new": "[1]为了那个时候[3]母亲终于睁开眼睛，[6]盯着我。[8]那只眼睛看起来很困惑。[11]我说了。[13]那句话变得刺骨，[16]成为楔子，[17]一直束缚着自己。",
    "checked": 0
  },
  {
    "old": "Vo_hou_0358",
    "new": "Vo_hou_0358"
  },
  {
    "old": "宝珠先輩は手を強く握る。感情を{顕/あらわ}すように。",
    "new": "宝珠前辈握着很强的手。为了表现感情。",
    "checked": 0
  },
  {
    "old": "ST_HO_13_0D",
    "new": "ST_HO_13_0D"
  },
  {
    "old": "[1]私の眼は[2]真実を{審/つまび}らかにする。[4]母の言葉は朱に染まっていて[7]それは怒りを意味する。[8]だから、[9]本当に私を疎んじていたのだと。",
    "new": "[1]我的眼睛[2]揭露真相[4]母亲的话染上了朱红色[7]那意味着愤怒。[8]所以，[9]真的是疏远了我。",
    "checked": 0
  },
  {
    "old": "Vo_hou_0359",
    "new": "Vo_hou_0359"
  },
  {
    "old": "[1]宝珠先輩……。",
    "new": "[1]宝珠前辈……。",
    "checked": 0
  },
  {
    "old": "Vo_alc_0633",
    "new": "Vo_alc_0633"
  },
  {
    "old": "……[#][1]でも、[2]大切な後輩から[4]誤解だと言われたのだと告げた。",
    "new": "……[#][1]但是，[2]从重要的后辈那里[4]我告诉她说是误会。",
    "checked": 0
  },
  {
    "old": "Vo_hou_0360",
    "new": "Vo_hou_0360"
  },
  {
    "old": "[1]怒りは私ではなく、[4]分家の人たちへ向けられたものだったのではないかって。[8]母は私を疎んじていたのではないのだって。[11]母は……。",
    "new": "[1]愤怒不是我，[4]是不是面向分家的人们的东西呢？[8]母亲并没有疏远我。[11]母亲……。",
    "checked": 0
  },
  {
    "old": "Vo_hou_0361",
    "new": "Vo_hou_0361"
  },
  {
    "old": "ST_HO_13_1E",
    "new": "ST_HO_13_1E"
  },
  {
    "old": "……[#][1]母は、[2]震える手を伸ばして[4]抱きしめてくれたわ。[7]誤解させてしまってごめんなさいって。[10]お披露目会で様子が変わって、[14]私が茶道を心から愉しめていないのを{識/し}っていた。",
    "new": "……[#][1]妈妈说，[2]伸出颤抖的手[4]抱紧了我。[7]让你误会了，对不起。[10]在发布会上，她的样子变了。[14]我知道我没有从心底里享受茶道。",
    "checked": 0
  },
  {
    "old": "Vo_hou_0362",
    "new": "Vo_hou_0362"
  },
  {
    "old": "ST_HO_11_3E",
    "new": "ST_HO_11_3E"
  },
  {
    "old": "[1]そして、[3]私が茶道を続けているのは[5]佐和良義の名が縛っているのではないかって……。[9]なら、[10]分家へ名を継がせるのも佳いかと考えていたそうなの……。",
    "new": "[1]然后，[3]我继续茶道的是[5]是不是被佐和良义的名字束缚住了……。[9]那么，[10]据说她在考虑让分家继承名字也很好……。",
    "checked": 0
  },
  {
    "old": "Vo_hou_0363",
    "new": "Vo_hou_0363"
  },
  {
    "old": "[1]ふたりとも想いがすれ違っていた……。",
    "new": "[1]两人的感情都有分歧……。",
    "checked": 0
  },
  {
    "old": "Vo_alc_0634",
    "new": "Vo_alc_0634"
  },
  {
    "old": "[1]ええ。[2]でも[3]それも正しく戻ることができた。[5]貴女のお陰よ、[6]アリス。",
    "new": "[1]嗯。[2]但是[3]那个也能正确地回来了。[5]多亏了你，[6]爱丽丝。",
    "checked": 0
  },
  {
    "old": "Vo_hou_0364",
    "new": "Vo_hou_0364"
  },
  {
    "old": "ev010a",
    "new": "ev010a"
  },
  {
    "old": "bgm05",
    "new": "bgm05"
  },
  {
    "old": "朱の瞳がわたしの瞳を愛おしく見詰めた。彼女に見詰められると寒さや、秋風が頬を撫でる感触、髪がなびく刺激――すべての感覚を一時的に忘れてしまった。",
    "new": "朱红色的眼睛爱惜地凝视着我的眼睛。被她盯着的话，寒冷、秋风抚摸脸颊的感觉、头发飘动的刺激——一时忘记了所有的感觉。",
    "checked": 0
  },
  {
    "old": "――佐和良義宝珠が幸せでいてくれている、",
    "new": "佐和良义宝珠很幸福。",
    "checked": 0
  },
  {
    "old": "それだけで佳い。それが佳い。",
    "new": "这样就够了。那很好。",
    "checked": 0
  },
  {
    "old": "[1]皆が祝福してくれている。",
    "new": "[1]大家都在祝福我。",
    "checked": 0
  },
  {
    "old": "Vo_alc_0635",
    "new": "Vo_alc_0635"
  },
  {
    "old": "メイも、宝珠先輩の母親も、",
    "new": "不管是小明还是宝珠前辈的母亲，",
    "checked": 0
  },
  {
    "old": "わたしの大切な友人たちも。",
    "new": "我重要的朋友们。",
    "checked": 0
  },
  {
    "old": "思わず溢れた言葉に、花が綻ぶように微笑む。わたしだけに向けられた笑顔。",
    "new": "不由得溢出的话语，仿佛绽放般微笑着。只对我的笑容。",
    "checked": 0
  },
  {
    "old": "ST_HO_13_2E",
    "new": "ST_HO_13_2E"
  },
  {
    "old": "[1]たくさんの想い出を作りましょう。[2]これから、[5]ずっと二人で。",
    "new": "[1]制造很多回忆吧。[2]从现在开始，[5]一直两个人。",
    "checked": 0
  },
  {
    "old": "Vo_hou_0365",
    "new": "Vo_hou_0365"
  },
  {
    "old": "ST_AL_03_1E",
    "new": "ST_AL_03_1E"
  },
  {
    "old": "[1]色々なことをしたいです。[2]学校帰りに買い食いをしたり、[5]落ち葉を集めてお芋を焼いたり、[8]わたしの家にも遊びに来てほしいです！",
    "new": "[1]我想做各种各样的事情。[2]在放学回家的路上买东西吃，[5]收集落叶烤芋头，[8]希望你也来我家玩！",
    "checked": 0
  },
  {
    "old": "Vo_alc_0636",
    "new": "Vo_alc_0636"
  },
  {
    "old": "[1]大好きな映画を二人で観て、[4]夜更かししながらたくさんお喋りをして――。",
    "new": "[1]两个人看了最喜欢的电影，[4]一边熬夜一边说很多话——。",
    "checked": 0
  },
  {
    "old": "Vo_alc_0637",
    "new": "Vo_alc_0637"
  },
  {
    "old": "――[1]素敵だわ。",
    "new": "——[1]太棒了。",
    "checked": 0
  },
  {
    "old": "Vo_hou_0366",
    "new": "Vo_hou_0366"
  },
  {
    "old": "ST_AL_03_0B",
    "new": "ST_AL_03_0B"
  },
  {
    "old": "[1]はい。[2]ふたりで色々なことを体験したい。[6]宝珠先輩とふたりでなら、[8]どんなことも素敵で、輝いてます！",
    "new": "[1]是的。[2]我想两个人体验各种各样的事情。[6]如果和宝珠前辈两个人的话，[8]无论做什么事都很棒，闪耀着光芒！",
    "checked": 0
  },
  {
    "old": "Vo_alc_0638",
    "new": "Vo_alc_0638"
  },
  {
    "old": "[1]二人で――。",
    "new": "[1]两个人——。",
    "checked": 0
  },
  {
    "old": "Vo_hou_0367",
    "new": "Vo_hou_0367"
  },
  {
    "old": "アリス、と囁く声が聞こえ吐息が頬にかかった。",
    "new": "听到爱丽丝的低声细语，叹息声挂在了脸颊上。",
    "checked": 0
  },
  {
    "old": "気がつくと彼女の頬は朱に染まり、瞳も同じく朱に潤んでいた。",
    "new": "回过神来，她的脸颊已经泛起了红晕，眼睛也湿润了。",
    "checked": 0
  },
  {
    "old": "ev010b",
    "new": "ev010b"
  },
  {
    "old": "秋のよう、",
    "new": "像秋天一样，",
    "checked": 0
  },
  {
    "old": "Vo_alc_0639",
    "new": "Vo_alc_0639"
  },
  {
    "old": "一陣の風が紅葉を散らし、佐和良義宝珠を鮮やかに彩った。",
    "new": "一阵风飘散了红叶，将佐和良义宝珠装点得鲜艳。",
    "checked": 0
  },
  {
    "old": "Vo_alc_0640",
    "new": "Vo_alc_0640"
  },
  {
    "old": "秋のような人と、わたしは――……",
    "new": "秋天一样的人和我——……",
    "checked": 0
  },
  {
    "old": "Vo_alc_0641",
    "new": "Vo_alc_0641"
  },
  {
    "old": "ev010c",
    "new": "ev010c"
  },
  {
    "old": "唇と唇を合わせた。",
    "new": "嘴唇和嘴唇合在一起。",
    "checked": 0
  },
  {
    "old": "Vo_alc_0642",
    "new": "Vo_alc_0642"
  },
  {
    "old": "それはとても甘く、",
    "new": "那是非常甜的，",
    "checked": 0
  },
  {
    "old": "Vo_alc_0643",
    "new": "Vo_alc_0643"
  },
  {
    "old": "とても親密で、",
    "new": "非常亲密，",
    "checked": 0
  },
  {
    "old": "Vo_alc_0644",
    "new": "Vo_alc_0644"
  },
  {
    "old": "神田アリスの中で秋がとどまった気がした。",
    "new": "感觉神田爱丽丝中秋天停了下来。",
    "checked": 0
  },
  {
    "old": "Vo_alc_0645",
    "new": "Vo_alc_0645"
  },
  {
    "old": "Vo_alc_0646",
    "new": "Vo_alc_0646"
  },
  {
    "old": "季節は巡る。",
    "new": "季节在循环。",
    "checked": 0
  },
  {
    "old": "Vo_alc_0647",
    "new": "Vo_alc_0647"
  },
  {
    "old": "秋を過ぎ、さまざまな色で彩る季節たちへと。",
    "new": "秋天过去了，向着各种颜色点缀的季节们。",
    "checked": 0
  },
  {
    "old": "Vo_alc_0648",
    "new": "Vo_alc_0648"
  },
  {
    "old": "ゆっくりと――ふたり手を繋ぎ、季節を歩んでいこう。",
    "new": "慢慢地——牵着手，走上季节吧。",
    "checked": 0
  },
  {
    "old": "Vo_alc_0649",
    "new": "Vo_alc_0649"
  },
  {
    "old": "秋の温もりに触れながら――わたしは、そう心に決めたのです。",
    "new": "抚摸着秋天的温暖——我下定了这样的决心。",
    "checked": 0
  },
  {
    "old": "Vo_alc_0650",
    "new": "Vo_alc_0650"
  },
  {
    "old": "WHITE",
    "new": "WHITE"
  },
  {
    "old": "ED_MOVIE_1ST",
    "new": "ED_MOVIE_1ST"
  },
  {
    "old": "alice_ed",
    "new": "alice_ed"
  },
  {
    "old": "ED_MOVIE_END",
    "new": "ED_MOVIE_END"
  },
  {
    "old": "bg999",
    "new": "bg999"
  },
  {
    "old": "0",
    "new": "0"
  }
]