[
  {
    "old": "bg002",
    "new": "bg002"
  },
  {
    "old": "bgm03",
    "new": "bgm03"
  },
  {
    "old": "ST_AL_02_0D",
    "new": "ST_AL_02_0D"
  },
  {
    "old": "一章",
    "new": "第一章"
  },
  {
    "old": "アリス",
    "new": "爱丽丝"
  },
  {
    "old": "これで間違いはないと思うけど……。",
    "new": "我觉得这样就不会错了……"
  },
  {
    "old": "Vo_alc_0141",
    "new": "Vo_alc_0141"
  },
  {
    "old": "どうにも据わりの悪い気がする。",
    "new": "总觉得不太舒服。"
  },
  {
    "old": "わたしの推理に誤りでもあるのだろうか……。",
    "new": "我的推理有错误吗……"
  },
  {
    "old": "もう一度考えてみようと思うも、",
    "new": "我想再考虑一下，"
  },
  {
    "old": "ST_AL_01_1A",
    "new": "ST_AL_01_1A"
  },
  {
    "old": "……[#]あ、早く向かわなくちゃ！",
    "new": "……[#]啊，必须快点去！"
  },
  {
    "old": "Vo_alc_0142",
    "new": "Vo_alc_0142"
  },
  {
    "old": "待ち合わせに遅れてしまうと、わたしは大股で靄の中に沈む弓道場へと向かった。",
    "new": "约会迟到了，我就迈着大步去沉在雾霭中的弓道场。"
  },
  {
    "old": "eye008",
    "new": "eye008"
  },
  {
    "old": "BLACK",
    "new": "BLACK"
  },
  {
    "old": "胃が重くなるような気分で、",
    "new": "我感到胃里一阵沉重。"
  },
  {
    "old": "bg007",
    "new": "bg007"
  },
  {
    "old": "わたしは授業を受けていた。",
    "new": "我在上课。"
  },
  {
    "old": "bgm04",
    "new": "bgm04"
  },
  {
    "old": "あの日、佐和良義先輩やメイとともに真実を導き出そうとした。",
    "new": "那天，我和佐和良义前辈以及小明一起试图找出真相。"
  },
  {
    "old": "途中まではわたしの推察も当たっていたのだ。",
    "new": "直到一半，我的推测都是正确的。"
  },
  {
    "old": "だから、犯人をさらに追い詰めるためにわたしは助力のつもりで口を挟んだ。",
    "new": "所以，为了进一步追查犯人，我抱着帮助的心情插嘴。"
  },
  {
    "old": "けれど、",
    "new": "但是，"
  },
  {
    "old": "ST_AL_02_1G",
    "new": "ST_AL_02_1G"
  },
  {
    "old": "『それが誤りだった……』",
    "new": "“那是错误的……”"
  },
  {
    "old": "Vo_alc_0143",
    "new": "Vo_alc_0143"
  },
  {
    "old": "わたしが言った誤り。それが佐和良義先輩の段取りをおかしくしてしまったのだろう。",
    "new": "我说的错误。这让佐和良义前辈的规划变得奇怪了吧。"
  },
  {
    "old": "犯人は分かり、謎は解けたけれど、皆へ消えないしこりを残す結果となった。",
    "new": "犯人是知道了，谜是解开了，但结果却给大家留下了无法消失的疙瘩。"
  },
  {
    "old": "春日＠？？？",
    "new": "春日＠？？？"
  },
  {
    "old": "んだ……さん。",
    "new": "田……同学。"
  },
  {
    "old": "Vo_kas_0012",
    "new": "Vo_kas_0012"
  },
  {
    "old": "ST_KS_01_0F",
    "new": "ST_KS_01_0F"
  },
  {
    "old": "春日",
    "new": "春日"
  },
  {
    "old": "神田さん――！",
    "new": "神田同学——！"
  },
  {
    "old": "Vo_kas_0013",
    "new": "Vo_kas_0013"
  },
  {
    "old": "え、あ……。",
    "new": "啊，啊……"
  },
  {
    "old": "Vo_alc_0144",
    "new": "Vo_alc_0144"
  },
  {
    "old": "机を揺らされ、顔を上げると教壇の先生が教科書を指し叩いていた。",
    "new": "她摇晃着桌子，抬头一看，讲台上的老师正指着教科书。"
  },
  {
    "old": "ST_KS_01_0B",
    "new": "ST_KS_01_0B"
  },
  {
    "old": "１５４ページからだよ。",
    "new": "从１５４页开始。"
  },
  {
    "old": "Vo_kas_0014",
    "new": "Vo_kas_0014"
  },
  {
    "old": "教えてくれる春日さんへありがとうと言うと、教科書を音読する。",
    "new": "我对教我的春日说了声谢谢，然后开始朗读教科书。"
  },
  {
    "old": "話していてもまったく頭に入ってこない。",
    "new": "说话也完全不想进去。"
  },
  {
    "old": "『……どうしたらいいの？』",
    "new": "“……怎么办才好呢？”"
  },
  {
    "old": "Vo_alc_0145",
    "new": "Vo_alc_0145"
  },
  {
    "old": "己の過ちの重さを胃と心に受けながら、覇気のない声は教室へと寒々しく響いたのだった…………。",
    "new": "胃和心承受着自己错误的重量，没有霸气的声音在教室里冷冷地响起…………"
  },
  {
    "old": "end001",
    "new": "end001"
  },
  {
    "old": "0",
    "new": "0"
  },
  {
    "old": "NONE",
    "new": "NONE"
  },
  {
    "old": "WHITE",
    "new": "WHITE"
  },
  {
    "old": "bg002",
    "new": "bg002"
  }
]